awq/__init__.py
awq/evaluation/__init__.py
awq/evaluation/eval_utils.py
awq/evaluation/humaneval_utils.py
awq/evaluation/kl_divergence.py
awq/models/__init__.py
awq/models/_config.py
awq/models/aquila.py
awq/models/auto.py
awq/models/baichuan.py
awq/models/base.py
awq/models/bloom.py
awq/models/cohere.py
awq/models/deepseek_v2.py
awq/models/exaone.py
awq/models/falcon.py
awq/models/gemma.py
awq/models/gemma2.py
awq/models/gpt_bigcode.py
awq/models/gpt_neox.py
awq/models/gptj.py
awq/models/internlm2.py
awq/models/llama.py
awq/models/llava.py
awq/models/llava_next.py
awq/models/minicpm.py
awq/models/minicpm3.py
awq/models/mistral.py
awq/models/mixtral.py
awq/models/mpt.py
awq/models/opt.py
awq/models/phi3.py
awq/models/phi3_v.py
awq/models/qwen.py
awq/models/qwen2.py
awq/models/qwen2vl.py
awq/models/stablelm.py
awq/models/starcoder2.py
awq/models/yi.py
awq/modules/__init__.py
awq/modules/act.py
awq/modules/fused/__init__.py
awq/modules/fused/attn.py
awq/modules/fused/block.py
awq/modules/fused/cache.py
awq/modules/fused/mlp.py
awq/modules/fused/model.py
awq/modules/fused/moe.py
awq/modules/fused/norm.py
awq/modules/linear/__init__.py
awq/modules/linear/exllama.py
awq/modules/linear/exllamav2.py
awq/modules/linear/gemm.py
awq/modules/linear/gemm_ipex.py
awq/modules/linear/gemv.py
awq/modules/linear/gemv_fast.py
awq/modules/linear/marlin.py
awq/modules/triton/__init__.py
awq/modules/triton/gemm.py
awq/quantize/__init__.py
awq/quantize/quantizer.py
awq/quantize/scale.py
awq/utils/__init__.py
awq/utils/calib_data.py
awq/utils/fused_utils.py
awq/utils/module.py
awq/utils/packing_utils.py
awq/utils/parallel.py
awq/utils/quant_utils.py
awq/utils/qwen_vl_utils.py
awq/utils/utils.py
autoawq-0.2.7.post3.dist-info/LICENSE
autoawq-0.2.7.post3.dist-info/METADATA
autoawq-0.2.7.post3.dist-info/WHEEL
autoawq-0.2.7.post3.dist-info/top_level.txt
autoawq-0.2.7.post3.dist-info/RECORD
