Metadata-Version: 2.1
Name: autoawq
Version: 0.2.7.post3
Summary: AutoAWQ implements the AWQ algorithm for 4-bit quantization with a 2x speedup during inference.
Home-page: https://github.com/casper-hansen/AutoAWQ
Author: Casper Hansen
License: MIT
Keywords: awq,autoawq,quantization,transformers
Platform: linux
Platform: windows
Classifier: Environment :: GPU :: NVIDIA CUDA :: 11.8
Classifier: Environment :: GPU :: NVIDIA CUDA :: 12
Classifier: License :: OSI Approved :: MIT License
Classifier: Natural Language :: English
Classifier: Programming Language :: Python :: 3.9
Classifier: Programming Language :: Python :: 3.10
Classifier: Programming Language :: Python :: 3.11
Classifier: Programming Language :: Python :: 3.12
Classifier: Programming Language :: C++
Requires-Python: >=3.8.0
License-File: LICENSE
Requires-Dist: torch>=2.2.0
Requires-Dist: triton
Requires-Dist: transformers>=4.45.0
Requires-Dist: tokenizers>=0.12.1
Requires-Dist: typing_extensions>=4.8.0
Requires-Dist: accelerate
Requires-Dist: datasets>=2.20
Requires-Dist: zstandard
Requires-Dist: huggingface_hub>=0.26.5
Provides-Extra: eval
Requires-Dist: lm_eval==0.4.1; extra == "eval"
Requires-Dist: tabulate; extra == "eval"
Requires-Dist: protobuf; extra == "eval"
Requires-Dist: evaluate; extra == "eval"
Requires-Dist: scipy; extra == "eval"
Provides-Extra: dev
Requires-Dist: black; extra == "dev"
Requires-Dist: mkdocstrings-python; extra == "dev"
Requires-Dist: mkdocs-material; extra == "dev"
Requires-Dist: griffe-typingdoc; extra == "dev"
Provides-Extra: cpu
Requires-Dist: intel-extension-for-pytorch>=2.4.0; extra == "cpu"
Provides-Extra: kernels
Requires-Dist: autoawq-kernels; extra == "kernels"
Requires-Dist: flash-attn>=2.2.0; extra == "kernels"
